weasypdf/__init__.py
weasypdf/apps.py
weasypdf/plot.py
weasypdf/urls.py
weasypdf/utils.py
weasypdf/views.py
weasypdf/management/__init__.py
weasypdf/management/commands/__init__.py
weasypdf/management/commands/build_test_pdf.py
weasypdf/static/weasypdf/images/header_left.png
weasypdf/templates/weasypdf/base.html
weasypdf/templates/weasypdf/base_nomargins.html
weasypdf/templates/weasypdf/footer.html
weasypdf/templates/weasypdf/header.html
weasypdf/templates/weasypdf/styles.css
weasypdf/templates/weasypdf/pages/test.css
weasypdf/templates/weasypdf/pages/test.html
django_weasypdf-0.1.2.dist-info/LICENSE
django_weasypdf-0.1.2.dist-info/METADATA
django_weasypdf-0.1.2.dist-info/WHEEL
django_weasypdf-0.1.2.dist-info/top_level.txt
django_weasypdf-0.1.2.dist-info/RECORD
