Metadata-Version: 2.1
Name: django-weasypdf
Version: 0.1.2
Summary: A Django class-based view helper to generate PDF with WeasyPrint
Home-page: http://github.com/morlandi/django-weasypdf
Author: Mario Orlandi
Author-email: morlandi@brainstorm.it
License: MIT
License-File: LICENSE
